dismal/blocking.py
dismal/bootstrap.py
dismal/callset.py
dismal/demesrepresentation.py
dismal/demographicmodel.py
dismal/demography.py
dismal/markov_matrices.py
dismal/model_instance.py
dismal/models.py
dismal/modelsimulation.py
dismal/multimodel.py
dismal/print_results.py
dismal-0.1.19b0.dist-info/LICENSE
dismal-0.1.19b0.dist-info/METADATA
dismal-0.1.19b0.dist-info/WHEEL
dismal-0.1.19b0.dist-info/top_level.txt
dismal-0.1.19b0.dist-info/RECORD
