Metadata-Version: 2.1
Name: dismal
Version: 0.1.19b0
Summary: Demographic inference from the distribution of pairwise segregating sites
License-File: LICENSE
Requires-Dist: numpy
Requires-Dist: pandas
Requires-Dist: setuptools
Requires-Dist: pyranges ==0.0.129
Requires-Dist: scikit-allel
Requires-Dist: demes
Requires-Dist: demesdraw
Requires-Dist: matplotlib
Requires-Dist: msprime
Requires-Dist: seaborn
Requires-Dist: tqdm
Requires-Dist: tskit
Requires-Dist: prettytable
Requires-Dist: joblib
